lb_matching_tools/__init__.py
lb_matching_tools/cleaner.py
lb_matching_tools/guff.py
lb_matching_tools-2024.1.30.1.dist-info/LICENSE
lb_matching_tools-2024.1.30.1.dist-info/METADATA
lb_matching_tools-2024.1.30.1.dist-info/WHEEL
lb_matching_tools-2024.1.30.1.dist-info/top_level.txt
lb_matching_tools-2024.1.30.1.dist-info/RECORD
