Metadata-Version: 2.1
Name: lb-matching-tools
Version: 2024.1.30.1
Summary: ListenBrainz tools for matching metadata to and from MusicBrainz.
Author-email: Robert Kaye <rob@metabrainz.org>
Project-URL: Homepage, https://github.com/metabrainz/listenbrainz-matching-tools
Classifier: Programming Language :: Python :: 3
Classifier: License :: OSI Approved :: GNU General Public License v2 (GPLv2)
Classifier: Operating System :: OS Independent
Requires-Python: >=3.8
License-File: LICENSE
Requires-Dist: regex
Provides-Extra: build
Requires-Dist: build ; extra == 'build'
Requires-Dist: twine ; extra == 'build'
Provides-Extra: tests
Requires-Dist: pytest ==7.1.2 ; extra == 'tests'
Requires-Dist: pytest-cov ==4.1.0 ; extra == 'tests'
